matchtube/__init__.py
matchtube/matchtube.py
matchtube-0.1.0.dist-info/DESCRIPTION.rst
matchtube-0.1.0.dist-info/METADATA
matchtube-0.1.0.dist-info/RECORD
matchtube-0.1.0.dist-info/WHEEL
matchtube-0.1.0.dist-info/entry_points.txt
matchtube-0.1.0.dist-info/metadata.json
matchtube-0.1.0.dist-info/top_level.txt
