Metadata-Version: 2.0
Name: matchtube
Version: 0.1.0
Summary: Match video titles on YouTube
Home-page: https://www.github.com/ritiek/matchtube
Author: Ritiek Malhotra
Author-email: ritiekmalhotra123@gmail.com
License: MIT
Download-URL: https://github.com/ritiek/scribd-downloader/archive/v0.1.0.tar.gz
Keywords: matchtube,YouTube,command-line,python,match
Platform: UNKNOWN
Requires-Dist: pafy
